cbuff/__init__.py
cbuff/main.py
cbuff/settings.py
cbuff-1.0.1.dist-info/METADATA
cbuff-1.0.1.dist-info/WHEEL
cbuff-1.0.1.dist-info/entry_points.txt
cbuff-1.0.1.dist-info/top_level.txt
cbuff-1.0.1.dist-info/RECORD
