Metadata-Version: 2.1
Name: cbuff
Version: 1.0.1
Summary: A command buffer for terminals.
Home-page: https://github.com/RaghavGohil/cbuff
Author: RaghavGohil
Author-email: raghavgohil2004@gmail.com
License: MIT LICENSE
Keywords: command buffer terminal storage windows linux macos
Platform: UNKNOWN
Classifier: Development Status :: 1 - Planning
Classifier: License :: OSI Approved :: MIT License
Classifier: Operating System :: Microsoft
Requires-Python: >=3.0
Requires-Dist: readme-renderer >=21.0
